SFI/OLI_bases.py
SFI/OLI_inference.py
SFI/SFI_Langevin.py
SFI/SFI_base_inference.py
SFI/SFI_data.py
SFI/SFI_plotting_toolkit.py
SFI/SFI_sparsity.py
SFI/SFI_utils.py
SFI/ULI_bases.py
SFI/ULI_inference.py
SFI/__init__.py
stochasticforceinference-1.9.5.2.dist-info/METADATA
stochasticforceinference-1.9.5.2.dist-info/WHEEL
stochasticforceinference-1.9.5.2.dist-info/top_level.txt
stochasticforceinference-1.9.5.2.dist-info/RECORD
