Metadata-Version: 2.4
Name: stochasticforceinference
Version: 1.9.5.2
Summary: Stochastic Force Inference for Langevin SDEs
Author-email: Pierre Ronceray <pierre.ronceray@univ-amu.fr>
License: MIT
Project-URL: Homepage, https://github.com/ronceray/StochasticForceInference
Requires-Python: >=3.11
Requires-Dist: numpy
Requires-Dist: scipy
Requires-Dist: jax>=0.6
Requires-Dist: jaxlib
Requires-Dist: pandas
Requires-Dist: matplotlib
Requires-Dist: pyyaml
Provides-Extra: dev
Requires-Dist: pytest; extra == "dev"
Requires-Dist: ruff; extra == "dev"
Requires-Dist: mypy; extra == "dev"
Requires-Dist: pre-commit; extra == "dev"
